odoo10_addon_l10n_br_base-10.0.1.0.0.99.dev69-nspkg.pth
odoo/addons/l10n_br_base/README.rst
odoo/addons/l10n_br_base/__init__.py
odoo/addons/l10n_br_base/__manifest__.py
odoo/addons/l10n_br_base/data/l10n_br_base.city.csv
odoo/addons/l10n_br_base/data/l10n_br_base_data.xml
odoo/addons/l10n_br_base/data/res.bank.csv
odoo/addons/l10n_br_base/data/res.country.state.csv
odoo/addons/l10n_br_base/data/res_company_data.xml
odoo/addons/l10n_br_base/demo/l10n_br_base_demo.xml
odoo/addons/l10n_br_base/demo/res_company_demo.xml
odoo/addons/l10n_br_base/demo/res_partner_demo.xml
odoo/addons/l10n_br_base/i18n/l10n_br_base.pot
odoo/addons/l10n_br_base/migrations/10.0.1.0.0/openupgrade_analysis.txt
odoo/addons/l10n_br_base/migrations/10.0.1.0.0/pre-migration.py
odoo/addons/l10n_br_base/migrations/8.0.1.0.1/openupgrade_analysis.txt
odoo/addons/l10n_br_base/migrations/8.0.1.0.1/openupgrade_analysis_work.txt
odoo/addons/l10n_br_base/models/__init__.py
odoo/addons/l10n_br_base/models/l10n_br_base.py
odoo/addons/l10n_br_base/models/res_bank.py
odoo/addons/l10n_br_base/models/res_company.py
odoo/addons/l10n_br_base/models/res_config.py
odoo/addons/l10n_br_base/models/res_country.py
odoo/addons/l10n_br_base/models/res_partner.py
odoo/addons/l10n_br_base/security/ir.model.access.csv
odoo/addons/l10n_br_base/static/description/icon.png
odoo/addons/l10n_br_base/static/img/res_partner_akretion-image.jpg
odoo/addons/l10n_br_base/tests/__init__.py
odoo/addons/l10n_br_base/tests/test_amount_to_text.py
odoo/addons/l10n_br_base/tests/test_base_onchange.py
odoo/addons/l10n_br_base/tests/test_base_validate_ie.py
odoo/addons/l10n_br_base/tests/test_other_ie.py
odoo/addons/l10n_br_base/tests/test_tools_fiscal.py
odoo/addons/l10n_br_base/tests/test_valid_createid.py
odoo/addons/l10n_br_base/tools/__init__.py
odoo/addons/l10n_br_base/tools/fiscal.py
odoo/addons/l10n_br_base/tools/misc.py
odoo/addons/l10n_br_base/views/l10n_br_base_view.xml
odoo/addons/l10n_br_base/views/res_bank_view.xml
odoo10_addon_l10n_br_base-10.0.1.0.0.99.dev69.dist-info/METADATA
odoo10_addon_l10n_br_base-10.0.1.0.0.99.dev69.dist-info/WHEEL
odoo10_addon_l10n_br_base-10.0.1.0.0.99.dev69.dist-info/namespace_packages.txt
odoo10_addon_l10n_br_base-10.0.1.0.0.99.dev69.dist-info/top_level.txt
odoo10_addon_l10n_br_base-10.0.1.0.0.99.dev69.dist-info/RECORD
